eventlytics_summarizer/__init__.py
eventlytics_summarizer/main.py
eventlytics_summarizer/prompts.py
eventlytics_summarizer-2025.12.21101526.dist-info/METADATA
eventlytics_summarizer-2025.12.21101526.dist-info/WHEEL
eventlytics_summarizer-2025.12.21101526.dist-info/top_level.txt
eventlytics_summarizer-2025.12.21101526.dist-info/RECORD
