Metadata-Version: 2.4
Name: eventlytics-summarizer
Version: 2025.12.21101526
Summary: A new package is designed to facilitate structured and reliable interactions with language models to generate concise summaries and extract key information from user-provided texts related to specific
Author-email: eventlytics-summarizer <hi@eugene.plus>
License: MIT
Project-URL: Homepage, https://github.com/chigwell/eventlytics-summarizer
Requires-Python: >=3.9
Requires-Dist: langchain-llm7>=0.0.0
Requires-Dist: llmatch-messages>=0.0.0
Requires-Dist: langchain-core>=0.3.0
